nyaml/__init__.py
nyaml/cli.py
nyaml/comment_collector.py
nyaml/helper.py
nyaml/nxdl2nyaml.py
nyaml/nyaml2nxdl.py
nyaml-0.2.3.dist-info/licenses/LICENSE
nyaml-0.2.3.dist-info/METADATA
nyaml-0.2.3.dist-info/WHEEL
nyaml-0.2.3.dist-info/entry_points.txt
nyaml-0.2.3.dist-info/top_level.txt
nyaml-0.2.3.dist-info/RECORD
