Metadata-Version: 2.4
Name: nyaml
Version: 0.2.3
Summary: A tool to convert NeXus definitions from NXDL/XML format to YAML and vice versa.
Author: The NOMAD Authors
License: 
Project-URL: Homepage, https://github.com/FAIRmat-NFDI/nyaml
Project-URL: Bug Tracker, https://github.com/FAIRmat-NFDI/nyaml/issues
Classifier: Programming Language :: Python :: 3.9
Classifier: Programming Language :: Python :: 3.10
Classifier: Programming Language :: Python :: 3.11
Classifier: Programming Language :: Python :: 3.12
Classifier: Programming Language :: Python :: 3.13
Classifier: License :: OSI Approved :: Apache Software License
Classifier: Operating System :: OS Independent
Requires-Python: >=3.9
License-File: LICENSE
Requires-Dist: click
Requires-Dist: lxml
Requires-Dist: pyyaml
Provides-Extra: dev
Requires-Dist: mypy; extra == "dev"
Requires-Dist: ruff>=0.12.0; extra == "dev"
Requires-Dist: pytest; extra == "dev"
Requires-Dist: types-lxml; extra == "dev"
Requires-Dist: pip-tools; extra == "dev"
Requires-Dist: pre-commit; extra == "dev"
Requires-Dist: types-pyyaml; extra == "dev"
Requires-Dist: lxml-stubs; extra == "dev"
Provides-Extra: docs
Requires-Dist: mkdocs; extra == "docs"
Requires-Dist: mkdocs-mermaid2-plugin; extra == "docs"
Requires-Dist: mkdocstrings; extra == "docs"
Requires-Dist: mkdocs-click; extra == "docs"
Requires-Dist: mkdocs-material; extra == "docs"
Dynamic: license-file
